[
    {
        "name": "Human",
        "size": "Medium",
        "type": "Humanoid",
        "subtype": "Human",
        "base_speed": 30,
        "ability_adjustments": {
            "strength": 0,
            "dexterity": 0,
            "constitution": 0,
            "intelligence": 0,
            "wisdom": 0,
            "charisma": 0
        },
        "racial_traits": [
            {
                "name": "Extra Feat",
                "description": "Humans gain one extra feat at 1st level."
            },
            {
                "name": "Extra Skill Points",
                "description": "Humans gain 4 extra skill points at 1st level and 1 extra skill point at each additional level."
            },
            {
                "name": "Favored Class",
                "description": "Any. When determining whether a multiclass human takes an experience point penalty, his or her highest-level class does not count."
            }
        ],
        "automatic_languages": [
            "Common"
        ],
        "bonus_languages": [
            "Any (other than secret languages)"
        ],
        "level_adjustment": 0,
        "description": "Most human societies are a mix of good and evil, with a strong focus on law and order. They tend to be fairly balanced in all respects."
    },
    {
        "name": "Dwarf",
        "size": "Medium",
        "type": "Humanoid",
        "subtype": "Dwarf",
        "base_speed": 20,
        "ability_adjustments": {
            "strength": 0,
            "dexterity": 0,
            "constitution": 2,
            "intelligence": 0,
            "wisdom": 0,
            "charisma": -2
        },
        "racial_traits": [
            {
                "name": "Darkvision",
                "description": "Dwarves can see in the dark up to 60 feet. Darkvision is black and white only, but it is otherwise like normal sight."
            },
            {
                "name": "Weapon Familiarity",
                "description": "Dwarves may treat dwarven waraxes and dwarven urgroshes as martial weapons, rather than exotic weapons."
            },
            {
                "name": "Stability",
                "description": "A dwarf gains a +4 bonus on ability checks made to resist being bull rushed or tripped when standing on the ground (but not when climbing, flying, riding, or otherwise not standing firmly on the ground)."
            },
            {
                "name": "Stonecunning",
                "description": "+2 racial bonus on Search checks to notice unusual stonework, such as sliding walls, stonework traps, new construction (even when built to match the old), unsafe stone surfaces, shaky stone ceilings, and the like. Something that isn't stone but that is disguised as stone also counts as unusual stonework. A dwarf who merely comes within 10 feet of unusual stonework can make a Search check as if he were actively searching, and a dwarf can use the Search skill to find stonework traps as a rogue can. A dwarf can also intuit depth, sensing his approximate depth underground as naturally as a human can sense which way is up."
            },
            {
                "name": "Poison Resistance",
                "description": "+2 racial bonus on saving throws against poison."
            },
            {
                "name": "Spell Resistance",
                "description": "+2 racial bonus on saving throws against spells and spell-like effects."
            },
            {
                "name": "Combat Bonuses",
                "description": "+1 racial bonus on attack rolls against orcs and goblinoids. +4 dodge bonus to Armor Class against monsters of the giant type."
            },
            {
                "name": "Skill Bonuses",
                "description": "+2 racial bonus on Appraise checks that are related to stone or metal items. +2 racial bonus on Craft checks that are related to stone or metal."
            }
        ],
        "automatic_languages": [
            "Common",
            "Dwarven"
        ],
        "bonus_languages": [
            "Giant",
            "Gnome",
            "Goblin",
            "Orc",
            "Terran",
            "Undercommon"
        ],
        "favored_class": "Fighter",
        "level_adjustment": 0,
        "description": "Dwarves are known for their skill in warfare, their ability to withstand physical and magical punishment, their knowledge of the earth's secrets, their hard work, and their capacity for drinking ale."
    },
    {
        "name": "Elf",
        "size": "Medium",
        "type": "Humanoid",
        "subtype": "Elf",
        "base_speed": 30,
        "ability_adjustments": {
            "strength": 0,
            "dexterity": 2,
            "constitution": -2,
            "intelligence": 0,
            "wisdom": 0,
            "charisma": 0
        },
        "racial_traits": [
            {
                "name": "Low-Light Vision",
                "description": "An elf can see twice as far as a human in starlight, moonlight, torchlight, and similar conditions of poor illumination. She retains the ability to distinguish color and detail under these conditions."
            },
            {
                "name": "Weapon Proficiency",
                "description": "Elves receive the Martial Weapon Proficiency feats for the longsword, rapier, longbow (including composite longbow), and shortbow (including composite shortbow) as bonus feats."
            },
            {
                "name": "Keen Senses",
                "description": "+2 racial bonus on Listen, Search, and Spot checks. An elf who merely passes within 5 feet of a secret or concealed door is entitled to a Search check to notice it as if she were actively looking for it."
            },
            {
                "name": "Immunity to Sleep",
                "description": "Immunity to magic sleep effects."
            },
            {
                "name": "Enchantment Resistance",
                "description": "+2 racial saving throw bonus against enchantment spells or effects."
            }
        ],
        "automatic_languages": [
            "Common",
            "Elven"
        ],
        "bonus_languages": [
            "Draconic",
            "Gnoll",
            "Gnome",
            "Goblin",
            "Orc",
            "Sylvan"
        ],
        "favored_class": "Wizard",
        "level_adjustment": 0,
        "description": "Elves are known for their poetry, song, and magical arts, but when danger threatens they show great skill with weapons and strategy."
    },
    {
        "name": "Gnome",
        "size": "Small",
        "type": "Humanoid",
        "subtype": "Gnome",
        "base_speed": 20,
        "ability_adjustments": {
            "strength": -2,
            "dexterity": 0,
            "constitution": 2,
            "intelligence": 0,
            "wisdom": 0,
            "charisma": 0
        },
        "racial_traits": [
            {
                "name": "Small Size",
                "description": "+1 size bonus to Armor Class, +1 size bonus on attack rolls, +4 size bonus on Hide checks, -4 penalty on grapple checks, lifting and carrying limits 3/4 those of Medium characters."
            },
            {
                "name": "Low-Light Vision",
                "description": "A gnome can see twice as far as a human in starlight, moonlight, torchlight, and similar conditions of poor illumination. He retains the ability to distinguish color and detail under these conditions."
            },
            {
                "name": "Weapon Familiarity",
                "description": "Gnomes may treat gnome hooked hammers as martial weapons rather than exotic weapons."
            },
            {
                "name": "Combat Bonuses",
                "description": "+1 racial bonus on attack rolls against kobolds and goblinoids. +4 dodge bonus to Armor Class against monsters of the giant type (such as ogres, trolls, and hill giants)."
            },
            {
                "name": "Spell-Like Abilities",
                "description": "1/day—speak with animals (burrowing mammal only, duration 1 minute). A gnome with a Charisma score of at least 10 also has the following spell-like abilities: 1/day—dancing lights, ghost sound, prestidigitation. Caster level 1st; save DC 10 + gnome's Cha modifier + spell level."
            },
            {
                "name": "Skill Bonuses",
                "description": "+2 racial bonus on Listen checks. +2 racial bonus on Craft (alchemy) checks."
            }
        ],
        "automatic_languages": [
            "Common",
            "Gnome"
        ],
        "bonus_languages": [
            "Draconic",
            "Dwarven",
            "Elven",
            "Giant",
            "Goblin",
            "Orc"
        ],
        "favored_class": "Bard",
        "level_adjustment": 0,
        "description": "Gnomes are welcome in most human lands, but they are most at home in hilly, forested areas."
    },
    {
        "name": "Half-Elf",
        "size": "Medium",
        "type": "Humanoid",
        "subtype": "Elf",
        "base_speed": 30,
        "ability_adjustments": {
            "strength": 0,
            "dexterity": 0,
            "constitution": 0,
            "intelligence": 0,
            "wisdom": 0,
            "charisma": 0
        },
        "racial_traits": [
            {
                "name": "Low-Light Vision",
                "description": "A half-elf can see twice as far as a human in starlight, moonlight, torchlight, and similar conditions of poor illumination. She retains the ability to distinguish color and detail under these conditions."
            },
            {
                "name": "Immunity to Sleep",
                "description": "Immunity to magic sleep effects."
            },
            {
                "name": "Enchantment Resistance",
                "description": "+2 racial saving throw bonus against enchantment spells or effects."
            },
            {
                "name": "Keen Senses",
                "description": "+1 racial bonus on Listen, Search, and Spot checks."
            },
            {
                "name": "Elven Blood",
                "description": "For all effects related to race, a half-elf is considered an elf."
            },
            {
                "name": "Extra Skill Points",
                "description": "+1 extra skill point at 1st level and +1 extra skill point whenever they gain a level."
            },
            {
                "name": "Favored Class",
                "description": "Any. When determining whether a multiclass half-elf takes an experience point penalty, her highest-level class does not count."
            }
        ],
        "automatic_languages": [
            "Common",
            "Elven"
        ],
        "bonus_languages": [
            "Any (other than secret languages)"
        ],
        "level_adjustment": 0,
        "description": "Half-elves have no lands of their own, though they are welcome in human cities and somewhat less welcome in elven forests."
    },
    {
        "name": "Half-Orc",
        "size": "Medium",
        "type": "Humanoid",
        "subtype": "Orc",
        "base_speed": 30,
        "ability_adjustments": {
            "strength": 2,
            "dexterity": 0,
            "constitution": 0,
            "intelligence": -2,
            "wisdom": 0,
            "charisma": -2
        },
        "racial_traits": [
            {
                "name": "Darkvision",
                "description": "Half-orcs can see in the dark up to 60 feet. Darkvision is black and white only, but it is otherwise like normal sight."
            },
            {
                "name": "Orc Blood",
                "description": "For all effects related to race, a half-orc is considered an orc."
            }
        ],
        "automatic_languages": [
            "Common",
            "Orc"
        ],
        "bonus_languages": [
            "Draconic",
            "Giant",
            "Gnoll",
            "Goblin",
            "Abyssal"
        ],
        "favored_class": "Barbarian",
        "level_adjustment": 0,
        "description": "Half-orcs are the short-tempered and sullen result of human and orc pairings. They usually inherit the worst features of both parents."
    },
    {
        "name": "Halfling",
        "size": "Small",
        "type": "Humanoid",
        "subtype": "Halfling",
        "base_speed": 20,
        "ability_adjustments": {
            "strength": -2,
            "dexterity": 2,
            "constitution": 0,
            "intelligence": 0,
            "wisdom": 0,
            "charisma": 0
        },
        "racial_traits": [
            {
                "name": "Small Size",
                "description": "+1 size bonus to Armor Class, +1 size bonus on attack rolls, +4 size bonus on Hide checks, -4 penalty on grapple checks, lifting and carrying limits 3/4 those of Medium characters."
            },
            {
                "name": "Racial Bonuses",
                "description": "+2 racial bonus on Climb, Jump, and Move Silently checks."
            },
            {
                "name": "Luck Bonus",
                "description": "+1 racial bonus on all saving throws."
            },
            {
                "name": "Fear Resistance",
                "description": "+2 morale bonus on saving throws against fear. This bonus stacks with the halfling's +1 bonus on saving throws in general."
            },
            {
                "name": "Weapon Proficiency",
                "description": "+1 racial bonus on attack rolls with thrown weapons and slings."
            },
            {
                "name": "Keen Senses",
                "description": "+2 racial bonus on Listen checks."
            }
        ],
        "automatic_languages": [
            "Common",
            "Halfling"
        ],
        "bonus_languages": [
            "Dwarven",
            "Elven",
            "Gnome",
            "Goblin",
            "Orc"
        ],
        "favored_class": "Rogue",
        "level_adjustment": 0,
        "description": "Halflings are clever, capable opportunists. Halfling individuals and clans find room for themselves wherever they can."
    },
    {
        "name": "Aasimar",
        "size": "Medium",
        "type": "Outsider",
        "subtype": "Native",
        "base_speed": 30,
        "ability_adjustments": {
            "strength": 0,
            "dexterity": 0,
            "constitution": 0,
            "intelligence": 0,
            "wisdom": 2,
            "charisma": 2
        },
        "racial_traits": [
            {
                "name": "Darkvision",
                "description": "Aasimar can see in the dark up to 60 feet. Darkvision is black and white only, but it is otherwise like normal sight."
            },
            {
                "name": "Acid, Cold, and Electricity Resistance",
                "description": "Aasimar have resistance 5 against acid, cold, and electricity."
            },
            {
                "name": "Spell-Like Ability",
                "description": "Daylight once per day as a sorcerer of a level equal to the aasimar's class levels."
            },
            {
                "name": "Skill Bonuses",
                "description": "+2 racial bonus on Listen and Spot checks."
            }
        ],
        "automatic_languages": [
            "Common",
            "Celestial"
        ],
        "bonus_languages": [
            "Draconic",
            "Dwarven",
            "Elven",
            "Gnome",
            "Halfling",
            "Sylvan"
        ],
        "favored_class": "Paladin",
        "level_adjustment": 1,
        "description": "Aasimar are usually tall, good-looking, and generally pleasant. Some have a minor physical trait suggesting their heritage, such as silver hair, golden eyes, or an unnaturally intense stare."
    },
    {
        "name": "Tiefling",
        "size": "Medium",
        "type": "Outsider",
        "subtype": "Native",
        "base_speed": 30,
        "ability_adjustments": {
            "strength": 0,
            "dexterity": 2,
            "constitution": 0,
            "intelligence": 2,
            "wisdom": 0,
            "charisma": -2
        },
        "racial_traits": [
            {
                "name": "Darkvision",
                "description": "Tieflings can see in the dark up to 60 feet. Darkvision is black and white only, but it is otherwise like normal sight."
            },
            {
                "name": "Cold, Electricity, and Fire Resistance",
                "description": "Tieflings have resistance 5 against cold, electricity, and fire."
            },
            {
                "name": "Spell-Like Ability",
                "description": "Darkness once per day as a sorcerer of a level equal to the tiefling's class levels."
            },
            {
                "name": "Skill Bonuses",
                "description": "+2 racial bonus on Bluff and Hide checks."
            }
        ],
        "automatic_languages": [
            "Common",
            "Infernal"
        ],
        "bonus_languages": [
            "Draconic",
            "Dwarven",
            "Elven",
            "Gnome",
            "Goblin",
            "Halfling",
            "Orc"
        ],
        "favored_class": "Rogue",
        "level_adjustment": 1,
        "description": "Tieflings are sneaky, subtle, and generally conniving. They prefer to strike from ambush and usually avoid fair fights if they can."
    }
]